{"nodes": [{"id": "server_tests_emptyleadguard_test_js", "label": "emptyLeadGuard.test.js", "file_type": "code", "source_file": "server\\__tests__\\emptyLeadGuard.test.js", "source_location": "L1"}, {"id": "emptyleadguard_test_constructor", "label": "constructor()", "file_type": "code", "source_file": "server\\__tests__\\emptyLeadGuard.test.js", "source_location": "L33"}, {"id": "emptyleadguard_test_messages", "label": "messages()", "file_type": "code", "source_file": "server\\__tests__\\emptyLeadGuard.test.js", "source_location": "L34"}], "edges": [{"source": "server_tests_emptyleadguard_test_js", "target": "vitest", "relation": "imports_from", "confidence": "EXTRACTED", "source_file": "server\\__tests__\\emptyLeadGuard.test.js", "source_location": "L24", "weight": 1.0}, {"source": "server_tests_emptyleadguard_test_js", "target": "emptyleadguard_test_constructor", "relation": "contains", "confidence": "EXTRACTED", "source_file": "server\\__tests__\\emptyLeadGuard.test.js", "source_location": "L33", "weight": 1.0}, {"source": "server_tests_emptyleadguard_test_js", "target": "emptyleadguard_test_messages", "relation": "contains", "confidence": "EXTRACTED", "source_file": "server\\__tests__\\emptyLeadGuard.test.js", "source_location": "L34", "weight": 1.0}], "raw_calls": []}